[
	{
		"title":"Las 12 Piezas Cortas:<br />Teatro de Lenin Compres",
		"link":"",
		"img":"http://ecx.images-amazon.com/images/I/518VYatj%2BSL.jpg",
		"desc":"Short plays in Spanish.",
		"price":"US$ 9.99",
		"paypal":"FAZ5X3DJ9UD28"
	},
	{
		"title":"Lenino's Jack Rabbits",
		"link":"http://jackrabbits.lenino.net",
		"img":"jackrabbits/images/splash.png",
		"desc":"Playing Cards Based Board Game of Epic Quests in Wonderland.",
		"paypal":""
	},
	{
		"title":"Cards + Songs of Wisdom",
		"link":"",
		"img":"images/jackrabbitscards.png",
		"desc":"Deck of custom designed playing cards plus 10 Lenino songs downloads.",
		"price":"US$ 9.99",
		"paypal":"2V9FCHX6DGLJS"
	}
]